imetis/__init__.py
imetis/metisSettings.py
imetis/metisUtils.py
imetis-0.0.3.dist-info/METADATA
imetis-0.0.3.dist-info/WHEEL
imetis-0.0.3.dist-info/top_level.txt
imetis-0.0.3.dist-info/RECORD
