Metadata-Version: 2.1
Name: imetis
Version: 0.0.3
Summary: A Python SDK for Metis.
Home-page: https://github.com/Jovany-Rong/imetis
Author: Jovany-Rong
Author-email: amphlie@163.com
License: MIT Licence
Keywords: metis,imetis
Platform: UNKNOWN
Classifier: Programming Language :: Python :: 3
Classifier: License :: OSI Approved :: MIT License
Classifier: Operating System :: OS Independent
Requires-Python: >=3.6
Requires-Dist: requests
